ysfilemanager/__init__.py
ysfilemanager/_version.py
ysfilemanager/apps.py
ysfilemanager/quickparser.py
ysfilemanager/scp_importer.py
ysfilemanager/urls.py
ysfilemanager/filemanager/__init__.py
ysfilemanager/filemanager/base.py
ysfilemanager/filemanager/dir_repository.py
ysfilemanager/filemanager/mutableyangset.py
ysfilemanager/filemanager/repository.py
ysfilemanager/filemanager/utility.py
ysfilemanager/filemanager/yangset.py
ysfilemanager/filemanager/tests/__init__.py
ysfilemanager/filemanager/tests/test_base.py
ysfilemanager/filemanager/tests/test_dir_repository.py
ysfilemanager/filemanager/tests/test_doctests.py
ysfilemanager/filemanager/tests/test_mutableyangset.py
ysfilemanager/filemanager/tests/test_repository.py
ysfilemanager/filemanager/tests/test_utility.py
ysfilemanager/filemanager/tests/test_yangset.py
ysfilemanager/static/ysfilemanager/css/bootstrap-duallistbox.css
ysfilemanager/static/ysfilemanager/css/module.css
ysfilemanager/static/ysfilemanager/css/ysfilemanager.css
ysfilemanager/static/ysfilemanager/docs/.buildinfo
ysfilemanager/static/ysfilemanager/docs/create_repository.fjson
ysfilemanager/static/ysfilemanager/docs/create_repository.html
ysfilemanager/static/ysfilemanager/docs/define_yangset.fjson
ysfilemanager/static/ysfilemanager/docs/define_yangset.html
ysfilemanager/static/ysfilemanager/docs/download_schemas.fjson
ysfilemanager/static/ysfilemanager/docs/download_schemas.html
ysfilemanager/static/ysfilemanager/docs/environment.pickle
ysfilemanager/static/ysfilemanager/docs/genindex.fjson
ysfilemanager/static/ysfilemanager/docs/genindex.html
ysfilemanager/static/ysfilemanager/docs/git_schemas.fjson
ysfilemanager/static/ysfilemanager/docs/git_schemas.html
ysfilemanager/static/ysfilemanager/docs/globalcontext.json
ysfilemanager/static/ysfilemanager/docs/index.fjson
ysfilemanager/static/ysfilemanager/docs/index.html
ysfilemanager/static/ysfilemanager/docs/last_build
ysfilemanager/static/ysfilemanager/docs/manage.fjson
yangsuite_filemanager-1.9.12.dist-info/LICENSE.txt
yangsuite_filemanager-1.9.12.dist-info/METADATA
yangsuite_filemanager-1.9.12.dist-info/WHEEL
yangsuite_filemanager-1.9.12.dist-info/entry_points.txt
yangsuite_filemanager-1.9.12.dist-info/top_level.txt
yangsuite_filemanager-1.9.12.dist-info/RECORD
