Metadata-Version: 2.1
Name: yangsuite-filemanager
Version: 1.9.12
Summary: YANG Suite application for managing YANG files.
Home-page: https://developer.cisco.com/yangsuite
Author: Glenn Matthews
Author-email: glmatthe@cisco.com
License: Cisco End User License Agreement
Requires-Python: >=3.6
License-File: LICENSE.txt
Requires-Dist: yangsuite >=3.0.0
Requires-Dist: yangsuite-devices >=2.0.0
Requires-Dist: yangsuite-yangtree >=2.0.0
